[
  {
    "date": "29.12.2025",
    "dayOfWeek": "Monday",
    "lunch": [
      {
        "tr": "Şafak Çorba",
        "en": "Dawn Soup"
      },
      {
        "tr": "Sebzeli Tavuk Sote",
        "en": "Chicken Sauté with Vegetables"
      },
      {
        "tr": "Pırasa (Vegan)",
        "en": "Leek (Vegan)"
      },
      {
        "tr": "Peynirli Makarna",
        "en": "Mac and Cheese"
      },
      {
        "tr": "Pancarlı Bahçe Salata",
        "en": "Beetroot Garden Salad"
      }
    ],
    "dinner": [
      {
        "tr": "Börülce Çorba",
        "en": "Black-Eyed Pea Soup"
      },
      {
        "tr": "Et Döner (Dilim Patates)",
        "en": "Meat Doner (Sliced Potatoes)"
      },
      {
        "tr": "Kabak Musakka (Vegan)",
        "en": "Zucchini Moussaka (Vegan)"
      },
      {
        "tr": "Amasra Salata",
        "en": "Amasra Salad"
      },
      {
        "tr": "Kardüşü",
        "en": "Kardüşü"
      }
    ],
    "alternative": [
      {
        "tr": "Ezogelin Çorba",
        "en": "Ezogelin Soup"
      },
      {
        "tr": "Kaşarlı Köfte (Arpa Şehriye Pilavı)",
        "en": "Kashar Meatballs (Barley Noodle Pilaf)"
      },
      {
        "tr": "Mantı (Yoğurt)",
        "en": "Manti (Yogurt)"
      },
      {
        "tr": "Arpa Şehriye Pilavı",
        "en": "Barley Noodle Pilaf"
      },
      {
        "tr": "Ispanaklı Rulo Börek",
        "en": "Spinach Roll Borek"
      },
      {
        "tr": "Zeytinyağlı Bamya",
        "en": "Okra with Olive Oil"
      },
      {
        "tr": "Niş Salata",
        "en": "Nish Salad"
      },
      {
        "tr": "Yoğurt",
        "en": "Yogurt"
      },
      {
        "tr": "Pudingli Pasta",
        "en": "Pudding Cake"
      },
      {
        "tr": "Sütlaç",
        "en": "Rice Pudding"
      },
      {
        "tr": "Karagöz Tatlısı",
        "en": "Karagöz Dessert"
      },
      {
        "tr": "Muz",
        "en": "Banana"
      }
    ]
  },
  {
    "date": "30.12.2025",
    "dayOfWeek": "Tuesday",
    "lunch": [
      {
        "tr": "Gulaş Çorba",
        "en": "Goulash Soup"
      },
      {
        "tr": "Kıymalı Fırın Patates",
        "en": "Baked Potatoes with Ground Meat"
      },
      {
        "tr": "Fırın Patates (Vegan)",
        "en": "Baked Potatoes (Vegan)"
      },
      {
        "tr": "Kaşarlı Erişte",
        "en": "Noodles with Kashar Cheese"
      },
      {
        "tr": "Akdeniz Salata",
        "en": "Mediterranean Salad"
      }
    ],
    "dinner": [
      {
        "tr": "Sebze Çorba",
        "en": "Vegetable Soup"
      },
      {
        "tr": "Nohutlu Köfte",
        "en": "Meatballs with Chickpeas"
      },
      {
        "tr": "Nohut (Vegan)",
        "en": "Chickpeas (Vegan)"
      },
      {
        "tr": "Bulgur Pilavı",
        "en": "Bulgur Pilaf"
      },
      {
        "tr": "Yoğurt",
        "en": "Yogurt"
      }
    ],
    "alternative": [
      {
        "tr": "Tel Şehriye Çorba",
        "en": "Vermicelli Soup"
      },
      {
        "tr": "Köylüm Tavuk (Domatesli Pirinç Pilavı)",
        "en": "Köylüm Chicken (Tomato Rice Pilaf)"
      },
      {
        "tr": "Fırın Uskumru (Patates Kavurma,Tere-Roka)",
        "en": "Baked Mackerel (Fried Potatoes, Arugula)"
      },
      {
        "tr": "Domatesli Pirinç Pilavı",
        "en": "Tomato Rice Pilaf"
      },
      {
        "tr": "Fesleğen Soslu Spagetti",
        "en": "Spaghetti with Pesto Sauce"
      },
      {
        "tr": "Zeytinyağlı Patlıcan",
        "en": "Eggplant with Olive Oil"
      },
      {
        "tr": "Karışık Salata",
        "en": "Mixed Salad"
      },
      {
        "tr": "Yoğurt",
        "en": "Yogurt"
      },
      {
        "tr": "Tiramisu",
        "en": "Tiramisu"
      },
      {
        "tr": "Portakallı Keşkül",
        "en": "Orange Keskul"
      },
      {
        "tr": "Çikolatalı Revani",
        "en": "Chocolate Revani"
      },
      {
        "tr": "Elma",
        "en": "Apple"
      }
    ]
  },
  {
    "date": "31.12.2025",
    "dayOfWeek": "Wednesday",
    "lunch": [
      {
        "tr": "Domates Çorba",
        "en": "Tomato Soup"
      },
      {
        "tr": "Hindi Tandır (Kestaneli Pilav)",
        "en": "Turkey Tandoori (Chestnut Pilaf)"
      },
      {
        "tr": "Yufkada Mantarlı Dolma (Vegan)",
        "en": "Mushroom Filling in Phyllo (Vegan)"
      },
      {
        "tr": "Kış Salata",
        "en": "Winter Salad"
      },
      {
        "tr": "Sup",
        "en": "Sup"
      }
    ],
    "dinner": [
      {
        "tr": "Yoğurt Çorba",
        "en": "Yogurt Soup"
      },
      {
        "tr": "Piliç Izgara (Sebze Haşlama)",
        "en": "Grilled Chicken (Steamed Vegetables)"
      },
      {
        "tr": "İçli Köfte (Sebze Haşlama) (Vegan)",
        "en": "Stuffed Meatballs (Steamed Vegetables) (Vegan)"
      },
      {
        "tr": "Bahçıvan Usulü Makarna",
        "en": "Gardener Style Pasta"
      },
      {
        "tr": "Mandalina",
        "en": "Tangerine"
      }
    ],
    "alternative": [
      {
        "tr": "Kırmızı Mercimek Çorba",
        "en": "Red Lentil Soup"
      },
      {
        "tr": "Meksika Köfte (Dilim Patates)",
        "en": "Mexican Meatballs (Sliced Potatoes)"
      },
      {
        "tr": "Etli Bezelye",
        "en": "Peas with Meat"
      },
      {
        "tr": "Peynirli Gül Böreği",
        "en": "Cheese Rose Borek"
      },
      {
        "tr": "Bulgur Pilavı",
        "en": "Bulgur Pilaf"
      },
      {
        "tr": "Mücver (Yoğurt)",
        "en": "Mücver (Yogurt)"
      },
      {
        "tr": "Mevsim Salata",
        "en": "Seasonal Salad"
      },
      {
        "tr": "Yoğurt",
        "en": "Yogurt"
      },
      {
        "tr": "Donut",
        "en": "Donut"
      },
      {
        "tr": "Krokanlı Muhallebi",
        "en": "Croquant Muhallebi"
      },
      {
        "tr": "Lokma Tatlısı",
        "en": "Lokma Dessert"
      },
      {
        "tr": "Portakal",
        "en": "Orange"
      }
    ]
  },
  {
    "date": "01.01.2026",
    "dayOfWeek": "Thursday",
    "lunch": [
      {
        "tr": "Karnabahar Çorba",
        "en": "Cauliflower Soup"
      },
      {
        "tr": "Elbasan Köfte (Sebze Haşlama)",
        "en": "Elbasan Meatballs (Steamed Vegetables)"
      },
      {
        "tr": "Taze Fasulye (Vegan)",
        "en": "Green Beans (Vegan)"
      },
      {
        "tr": "Arpa Şehriye Pilavı",
        "en": "Barley Noodle Pilaf"
      },
      {
        "tr": "Yoğurt",
        "en": "Yogurt"
      }
    ],
    "dinner": [
      {
        "tr": "Minestrone Çorba",
        "en": "Minestrone Soup"
      },
      {
        "tr": "Kıymalı Ispanak (Yoğurt)",
        "en": "Spinach with Ground Meat (Yogurt)"
      },
      {
        "tr": "Ispanak (Vegan)",
        "en": "Spinach (Vegan)"
      },
      {
        "tr": "Su Böreği",
        "en": "Water Borek"
      },
      {
        "tr": "Elma",
        "en": "Apple"
      }
    ],
    "alternative": [
      {
        "tr": "Yarma Çorba",
        "en": "Yarma Soup"
      },
      {
        "tr": "Kıymalı Kibrit Kebap",
        "en": "Matchstick Kebab with Ground Meat"
      },
      {
        "tr": "Tavuk Külbastı (Sebzeli Pirinç Pilavı)",
        "en": "Chicken Külbastı (Vegetable Rice Pilaf)"
      },
      {
        "tr": "Sebzeli Pirinç Pilavı",
        "en": "Vegetable Rice Pilaf"
      },
      {
        "tr": "Erişte",
        "en": "Noodles"
      },
      {
        "tr": "Zeytinyağlı Barbunya",
        "en": "Borlotti Beans with Olive Oil"
      },
      {
        "tr": "Niş Salata",
        "en": "Nish Salad"
      },
      {
        "tr": "Yoğurt",
        "en": "Yogurt"
      },
      {
        "tr": "Çikolatalı Puding",
        "en": "Chocolate Pudding"
      },
      {
        "tr": "İncirli Keşkül",
        "en": "Fig Keskul"
      },
      {
        "tr": "Kemalpaşa Tatlısı",
        "en": "Kemalpaşa Dessert"
      },
      {
        "tr": "Muz",
        "en": "Banana"
      }
    ]
  },
  {
    "date": "02.01.2026",
    "dayOfWeek": "Friday",
    "lunch": [
      {
        "tr": "Mısır Çorba",
        "en": "Corn Soup"
      },
      {
        "tr": "Sicilya Usulü Tavuk (Püre)",
        "en": "Sicilian Style Chicken (Mashed Potatoes)"
      },
      {
        "tr": "Yufkada Pırasalı Dolma (Vegan)",
        "en": "Leek Filling in Phyllo (Vegan)"
      },
      {
        "tr": "Amasra Salata",
        "en": "Amasra Salad"
      },
      {
        "tr": "Sütlü İrmik Tatlısı",
        "en": "Semolina Pudding"
      }
    ],
    "dinner": [
      {
        "tr": "Tarhana Çorba",
        "en": "Tarhana Soup"
      },
      {
        "tr": "Tas Kebap",
        "en": "Tas Kebab"
      },
      {
        "tr": "Mantar Sote (Vegan)",
        "en": "Mushroom Sauté (Vegan)"
      },
      {
        "tr": "Bulgur Pilavı",
        "en": "Bulgur Pilaf"
      },
      {
        "tr": "Karışık Salata",
        "en": "Mixed Salad"
      }
    ],
    "alternative": [
      {
        "tr": "Kilis Çorba",
        "en": "Kilis Soup"
      },
      {
        "tr": "İzmir Köfte",
        "en": "Izmir Meatballs"
      },
      {
        "tr": "Karışık Musakka",
        "en": "Mixed Moussaka"
      },
      {
        "tr": "Soslu Spagetti",
        "en": "Spaghetti with Sauce"
      },
      {
        "tr": "Peynirli Rulo Börek",
        "en": "Cheese Roll Borek"
      },
      {
        "tr": "Havuç Kızartma (Yoğurt)",
        "en": "Fried Carrots (Yogurt)"
      },
      {
        "tr": "Pancarlı Bahçe Salata",
        "en": "Beetroot Garden Salad"
      },
      {
        "tr": "Yoğurt",
        "en": "Yogurt"
      },
      {
        "tr": "Kahveli Keşkül",
        "en": "Coffee Keskul"
      },
      {
        "tr": "Muhallebili Cezerye",
        "en": "Cezerye with Muhallebi"
      },
      {
        "tr": "Şöbiyet",
        "en": "Şöbiyet"
      },
      {
        "tr": "Mandalina",
        "en": "Tangerine"
      }
    ]
  },
  {
    "date": "03.01.2026",
    "dayOfWeek": "Saturday",
    "lunch": [
      {
        "tr": "Brokoli Çorba",
        "en": "Broccoli Soup"
      },
      {
        "tr": "Etli Kuru Fasulye",
        "en": "White Beans with Meat"
      },
      {
        "tr": "Kuru Fasulye (Vegan)",
        "en": "White Beans (Vegan)"
      },
      {
        "tr": "Pirinç Pilavı",
        "en": "Rice Pilaf"
      },
      {
        "tr": "Turşu",
        "en": "Pickles"
      }
    ],
    "dinner": [
      {
        "tr": "Şafak Çorba",
        "en": "Dawn Soup"
      },
      {
        "tr": "Köri Soslu Köfte",
        "en": "Meatballs with Curry Sauce"
      },
      {
        "tr": "Fırın Patates (Vegan)",
        "en": "Baked Potatoes (Vegan)"
      },
      {
        "tr": "Kaşarlı Cevizli Erişte",
        "en": "Noodles with Kashar Cheese and Walnuts"
      },
      {
        "tr": "Çilekli Puding",
        "en": "Strawberry Pudding"
      }
    ],
    "alternative": [
      {
        "tr": "Süleymaniye Çorba",
        "en": "Süleymaniye Soup"
      },
      {
        "tr": "Şişte Adana Kebap (Lavaş)",
        "en": "Adana Kebab on Skewer (Lavaş)"
      },
      {
        "tr": "Tavuklu Türkmen Kebap",
        "en": "Turkmen Kebab with Chicken"
      },
      {
        "tr": "Arpa Şehriye Pilavı",
        "en": "Barley Noodle Pilaf"
      },
      {
        "tr": "Fırın Makarna",
        "en": "Baked Pasta"
      },
      {
        "tr": "Zeytinyağlı Enginar",
        "en": "Artichoke with Olive Oil"
      },
      {
        "tr": "Akdeniz Salata",
        "en": "Mediterranean Salad"
      },
      {
        "tr": "Yoğurt",
        "en": "Yogurt"
      },
      {
        "tr": "Kadife Pasta",
        "en": "Velvet Cake"
      },
      {
        "tr": "Sultan Muhallebi",
        "en": "Sultan Muhallebi"
      },
      {
        "tr": "Damla Tatlısı",
        "en": "Damla Dessert"
      },
      {
        "tr": "Elma",
        "en": "Apple"
      }
    ]
  },
  {
    "date": "04.01.2026",
    "dayOfWeek": "Sunday",
    "lunch": [
      {
        "tr": "Alaca Çorba",
        "en": "Alaca Soup"
      },
      {
        "tr": "Orman Kebap",
        "en": "Forest Kebab"
      },
      {
        "tr": "Karnabahar (Vegan)",
        "en": "Cauliflower (Vegan)"
      },
      {
        "tr": "Pesto Soslu Makarna",
        "en": "Pasta with Pesto Sauce"
      },
      {
        "tr": "Portakal",
        "en": "Orange"
      }
    ],
    "dinner": [
      {
        "tr": "Kırmızı Mercimek Çorba",
        "en": "Red Lentil Soup"
      },
      {
        "tr": "Kıymalı Türlü",
        "en": "Türlü with Ground Meat"
      },
      {
        "tr": "Türlü (Vegan)",
        "en": "Türlü (Vegan)"
      },
      {
        "tr": "Bulgur Pilavı",
        "en": "Bulgur Pilaf"
      },
      {
        "tr": "Yoğurt",
        "en": "Yogurt"
      }
    ],
    "alternative": [
      {
        "tr": "Maş Fasulyesi Çorba",
        "en": "Mung Bean Soup"
      },
      {
        "tr": "Ispanaklı Tavuk",
        "en": "Chicken with Spinach"
      },
      {
        "tr": "Belen Köfte (Domatesli Pirinç Pilavı)",
        "en": "Belen Meatballs (Tomato Rice Pilaf)"
      },
      {
        "tr": "Domatesli Pirinç Pilavı",
        "en": "Tomato Rice Pilaf"
      },
      {
        "tr": "Patatesli Gül Böreği",
        "en": "Potato Rose Borek"
      },
      {
        "tr": "Zeytinyağlı Brüksel Lahana",
        "en": "Brussels Sprouts with Olive Oil"
      },
      {
        "tr": "Mevsim Salata",
        "en": "Seasonal Salad"
      },
      {
        "tr": "Yoğurt",
        "en": "Yogurt"
      },
      {
        "tr": "Mozaik Pasta",
        "en": "Mosaic Cake"
      },
      {
        "tr": "Fındıklı Keşkül",
        "en": "Hazelnut Keskul"
      },
      {
        "tr": "Susam Tatlısı",
        "en": "Sesame Dessert"
      },
      {
        "tr": "Muz",
        "en": "Banana"
      }
    ]
  },
  {
    "date": "05.01.2026",
    "dayOfWeek": "Monday",
    "lunch": [
      {
        "tr": "Sebze Çorba",
        "en": "Vegetable Soup"
      },
      {
        "tr": "Olimpiyat Köfte (Patates Kavurma)",
        "en": "Olympic Meatballs (Fried Potatoes)"
      },
      {
        "tr": "İçli Köfte (Domates - Biber) (Vegan)",
        "en": "Stuffed Meatballs (Tomato - Pepper) (Vegan)"
      },
      {
        "tr": "Kış Salata",
        "en": "Winter Salad"
      },
      {
        "tr": "Hira Tatlısı",
        "en": "Hira Dessert"
      }
    ],
    "dinner": [
      {
        "tr": "Domates Çorba",
        "en": "Tomato Soup"
      },
      {
        "tr": "Piliç Roti (Sebze Haşlama)",
        "en": "Chicken Roti (Steamed Vegetables)"
      },
      {
        "tr": "Patlıcan Kavurma (Vegan)",
        "en": "Eggplant Sauté (Vegan)"
      },
      {
        "tr": "Arpa Şehriye Pilavı",
        "en": "Barley Noodle Pilaf"
      },
      {
        "tr": "Ayran",
        "en": "Ayran"
      }
    ],
    "alternative": [
      {
        "tr": "Bulgur Çorba",
        "en": "Bulgur Soup"
      },
      {
        "tr": "Et Tiridi",
        "en": "Meat Tiridi"
      },
      {
        "tr": "Lahana Kapama",
        "en": "Cabbage Casserole"
      },
      {
        "tr": "Kaşarlı Erişte",
        "en": "Noodles with Kashar Cheese"
      },
      {
        "tr": "Mısırlı Pirinç Pilavı",
        "en": "Corn Rice Pilaf"
      },
      {
        "tr": "Zeytinyağlı Börülce",
        "en": "Black-Eyed Peas with Olive Oil"
      },
      {
        "tr": "Amasra Salata",
        "en": "Amasra Salad"
      },
      {
        "tr": "Yoğurt",
        "en": "Yogurt"
      },
      {
        "tr": "Çikolatalı Şarlot",
        "en": "Chocolate Charlotte"
      },
      {
        "tr": "Sakızlı Muhallebi",
        "en": "Mastic Muhallebi"
      },
      {
        "tr": "Elbasan Tatlısı",
        "en": "Elbasan Dessert"
      },
      {
        "tr": "Mandalina",
        "en": "Tangerine"
      }
    ]
  }
]